colas/__init__.py
colas/app.py
colas/py.typed
colas/queue.py
colas/results.py
colas/task.py
colas-0.1.2.dist-info/METADATA
colas-0.1.2.dist-info/WHEEL
colas-0.1.2.dist-info/licenses/LICENSE
colas-0.1.2.dist-info/RECORD
