Metadata-Version: 2.4
Name: colas
Version: 0.1.2
Summary: Modern task queue framework
Project-URL: Homepage, https://github.com/projazzka/colas
Author-email: Igor Prochazka <igor.prochazka@gmail.com>
License: MIT License
License-File: LICENSE
Requires-Python: >=3.13
Requires-Dist: aiosqlite>=0.21.0
Requires-Dist: asyncio>=3.4.3
Requires-Dist: asyncpg>=0.30.0
Requires-Dist: msgpack>=1.1.1
